recently_visited_page_middleware/__init__.py
recently_visited_page_middleware/asgi.py
recently_visited_page_middleware/middleware.py
recently_visited_page_middleware/settings.py
recently_visited_page_middleware/urls.py
recently_visited_page_middleware/utils.py
recently_visited_page_middleware/wsgi.py
recently_visited_page_middleware-0.1.2.dist-info/METADATA
recently_visited_page_middleware-0.1.2.dist-info/WHEEL
recently_visited_page_middleware-0.1.2.dist-info/top_level.txt
recently_visited_page_middleware-0.1.2.dist-info/RECORD
