Metadata-Version: 2.1
Name: recently-visited-page-middleware
Version: 0.1.2
Summary: Django middleware for tracking recently visited pages
Home-page: https://github.com/Abiorh001/recently_visited_page_middleware.git
Author: Abiola Adeshina
Author-email: abiolaadeshinaadedayo@gmail.com
License: UNKNOWN
Platform: UNKNOWN
Classifier: Development Status :: 3 - Alpha
Classifier: Framework :: Django
Classifier: Intended Audience :: Developers
Classifier: License :: OSI Approved :: MIT License
Classifier: Programming Language :: Python :: 3
Classifier: Programming Language :: Python :: 3.6
Classifier: Programming Language :: Python :: 3.7
Classifier: Programming Language :: Python :: 3.8
Classifier: Programming Language :: Python :: 3.9
Requires-Dist: Django
Requires-Dist: djangorestframework
